{
  "Items": [
    {
      "FormDefinitionId": "702499a4-f77b-4f8f-a0a6-abcd0134e520",
      "FormId": "1760647f-ad45-4153-8303-ac850097c0e9",
      "EventSection": "ESYDetermination",
      "FormState": "",
      "FormStatusKey": "Initial",
      "FormStatus": "Initial",
      "EventSectionGroupName": "<span class='hidden'>0000000035</span>ESY",
      "Name": "ESY Determination",
      "OrderNumber": "0000000001"
    },
    {
      "OrderNumber": "0000000001",
      "FormDefinitionId": "0f227d29-518f-456c-83d8-abbf01523af8",
      "FormId": "092f88dd-0c0c-4cde-94fe-ac850097c0e0",
      "EventSection": "AuditoryImpairment",
      "FormState": "",
      "FormStatusKey": "Initial",
      "FormStatus": "Initial",
      "EventSectionGroupName": "<span class='hidden'>0000000045</span>Supplements",
      "Name": "Auditory Impairment"
    },
    {
      "FormId": "",
      "EventSection": "ESYGoals",
      "FormState": "",
      "FormStatusKey": "",
      "FormStatus": "",
      "EventSectionGroupName": "<span class='hidden'>0000000035</span>ESY",
      "Name": "ESY Goals",
      "OrderNumber": "0000010000"
    },
    {
      "OrderNumber": "0000010001",
      "FormDefinitionId": "9784f0a6-b86f-42d4-bada-78d4b865c31b",
      "FormId": "f42fbd90-acd0-4266-92ea-ac850097c0db",
      "EventSection": "NoticeOfAction(PWNPR)",
      "FormState": "",
      "FormStatusKey": "Initial",
      "FormStatus": "Initial",
      "EventSectionGroupName": "<span class='hidden'>0000000027</span>Notices",
      "Name": "Notice Of Action (PWNPR)"
    },
    {
      "OrderNumber": "0000010001",
      "FormDefinitionId": "5db6c797-d745-4dee-968d-abd600e09774",
      "FormId": "13975a10-beb7-47de-b42c-ac850097c0e9",
      "EventSection": "AutismSpectrumDisorder",
      "FormState": "",
      "FormStatusKey": "Initial",
      "FormStatus": "Initial",
      "EventSectionGroupName": "<span class='hidden'>0000000045</span>Supplements",
      "Name": "Autism Spectrum Disorder"
    },
    {
      "OrderNumber": "0000010001",
      "FormDefinitionId": "2d87e6ec-92e1-412e-94d3-d8cc23bdd25c",
      "FormId": "b4f348bf-4c6e-406e-9a6b-ac850097c0db",
      "EventSection": "PriorWrittenNoticeofNon-ConsensusARD",
      "FormState": "",
      "FormStatusKey": "Initial",
      "FormStatus": "Initial",
      "EventSectionGroupName": "<span class='hidden'>0000000500</span>Forms",
      "Name": "Prior Written Notice of Non-Consensus ARD"
    },
    {
      "OrderNumber": "0000010001",
      "FormDefinitionId": "4a90823e-4c25-428b-a55c-33c86c26ffb0",
      "FormId": "f8f8d9aa-2d9b-46ad-b8c3-ac850097c0e0",
      "EventSection": "IndividualServicePlan(ISP)",
      "FormState": "",
      "FormStatusKey": "Initial",
      "FormStatus": "Initial",
      "EventSectionGroupName": "<span class='hidden'>0000000860</span>Service Plan",
      "Name": "Individual Service Plan (ISP)"
    },
    {
      "OrderNumber": "0000010010",
      "FormDefinitionId": "36d7ab59-3343-44bb-be85-62aa04bbe149",
      "FormId": "15c9a9ea-2232-4f62-b4a9-ac850097c0d1",
      "EventSection": "PresentLevels",
      "FormState": "*",
      "FormStatusKey": "Initial",
      "FormStatus": "Initial",
      "EventSectionGroupName": "<span class='hidden'>0000000025</span>Plan",
      "Name": "Present Levels"
    },
    {
      "OrderNumber": "0000010020",
      "FormDefinitionId": "aeab60e5-a578-4471-9a88-63d0a0475fed",
      "FormId": "47bfc68f-8c64-45f0-b38f-ac850097c0d1",
      "EventSection": "PresentLevels",
      "FormState": "*",
      "FormStatusKey": "Initial",
      "FormStatus": "Initial",
      "EventSectionGroupName": "<span class='hidden'>0000000025</span>Plan",
      "Name": "Curriculum and Learning Environment"
    },
    {
      "OrderNumber": "0000010030",
      "FormDefinitionId": "a0b84244-891b-4355-a8a1-3c1a3b4f4030",
      "FormId": "f4df4bb7-c797-4427-b558-ac850097c0e0",
      "EventSection": "PresentLevels",
      "FormState": "*",
      "FormStatusKey": "Initial",
      "FormStatus": "Initial",
      "EventSectionGroupName": "<span class='hidden'>0000000025</span>Plan",
      "Name": "Social or Emotional Behavior"
    },
    {
      "OrderNumber": "0000010040",
      "FormDefinitionId": "86b58193-1711-43f3-bb6a-996f68ac9053",
      "FormId": "9d1b40c9-9591-4628-b6a1-ac850097c0db",
      "EventSection": "PresentLevels",
      "FormState": "*",
      "FormStatusKey": "Initial",
      "FormStatus": "Initial",
      "EventSectionGroupName": "<span class='hidden'>0000000025</span>Plan",
      "Name": "Independent Functioning"
    },
    {
      "OrderNumber": "0000010050",
      "FormDefinitionId": "157e6df1-178f-4261-a2e6-beb357d33feb",
      "FormId": "bc875888-e284-476c-a924-ac850097c0d6",
      "EventSection": "PresentLevels",
      "FormState": "",
      "FormStatusKey": "Initial",
      "FormStatus": "Initial",
      "EventSectionGroupName": "<span class='hidden'>0000000025</span>Plan",
      "Name": "Health Care"
    },
    {
      "OrderNumber": "0000010060",
      "FormDefinitionId": "7f1107c6-e23b-4604-b2ff-d9854f515727",
      "FormId": "a058e027-e688-4956-87fc-ac850097c0d6",
      "EventSection": "PresentLevels",
      "FormState": "*",
      "FormStatusKey": "Initial",
      "FormStatus": "Initial",
      "EventSectionGroupName": "<span class='hidden'>0000000025</span>Plan",
      "Name": "Communication"
    },
    {
      "OrderNumber": "0000020000",
      "FormId": "",
      "EventSection": "ESYAccommodations",
      "FormState": "",
      "FormStatusKey": "",
      "FormStatus": "",
      "EventSectionGroupName": "<span class='hidden'>0000000035</span>ESY",
      "Name": "ESY Accommodations"
    },
    {
      "OrderNumber": "0000020000",
      "FormId": "",
      "EventSection": "EvaluativeAssessmentResults",
      "FormState": "",
      "FormStatusKey": "",
      "FormStatus": "",
      "EventSectionGroupName": "<span class='hidden'>0000000020</span>Evaluation",
      "Name": "Evaluative Assessment Results"
    },
    {
      "OrderNumber": "0000020000",
      "FormId": "",
      "EventSection": "Goals",
      "FormState": "",
      "FormStatusKey": "",
      "FormStatus": "",
      "EventSectionGroupName": "<span class='hidden'>0000000025</span>Plan",
      "Name": "Goals"
    },
    {
      "OrderNumber": "0000020000",
      "FormId": "",
      "EventSection": "StudentInformation",
      "FormState": "",
      "FormStatusKey": "",
      "FormStatus": "",
      "EventSectionGroupName": "<span class='hidden'>0000000000</span>Summary",
      "Name": "Student Information"
    },
    {
      "OrderNumber": "0000020001",
      "FormDefinitionId": "7cff39f4-1d87-4e5c-8307-ac2100cef6d6",
      "FormId": "91cfe369-f1b9-4955-a945-ac850097c0f7",
      "EventSection": "BehaviorInterventionPlan(BIP)",
      "FormState": "",
      "FormStatusKey": "Initial",
      "FormStatus": "Initial",
      "EventSectionGroupName": "<span class='hidden'>0000000045</span>Supplements",
      "Name": "Behavior Intervention Plan (BIP)"
    },
    {
      "OrderNumber": "0000020001",
      "FormDefinitionId": "82f81053-5a9d-49a1-81c9-abe50000f40d",
      "FormId": "2bca04bb-a9e7-4ce8-8f16-ac850097c0db",
      "EventSection": "MedicaidOne-TimeParentalConsent",
      "FormState": "*",
      "FormStatusKey": "Initial",
      "FormStatus": "Initial",
      "EventSectionGroupName": "<span class='hidden'>0000000500</span>Forms",
      "Name": "Medicaid One-Time Parental Consent"
    },
    {
      "OrderNumber": "0000030000",
      "FormId": "",
      "EventSection": "Accommodations",
      "FormState": "",
      "FormStatusKey": "",
      "FormStatus": "",
      "EventSectionGroupName": "<span class='hidden'>0000000025</span>Plan",
      "Name": "Accommodations"
    },
    {
      "OrderNumber": "0000030000",
      "FormId": "",
      "EventSection": "ESYAssistiveTechnology",
      "FormState": "",
      "FormStatusKey": "",
      "FormStatus": "",
      "EventSectionGroupName": "<span class='hidden'>0000000035</span>ESY",
      "Name": "ESY Assistive Technology"
    },
    {
      "OrderNumber": "0000030001",
      "FormDefinitionId": "aeab6591-31e4-4790-9ccb-51c2b795be15",
      "FormId": "39474d0e-9dfc-4aa3-9eb6-ac850097c0db",
      "EventSection": "Dyslexia%2FDysgraphia",
      "FormState": "",
      "FormStatusKey": "Initial",
      "FormStatus": "Initial",
      "EventSectionGroupName": "<span class='hidden'>0000000045</span>Supplements",
      "Name": "Dyslexia/Dysgraphia"
    },
    {
      "OrderNumber": "0000035001",
      "FormDefinitionId": "4fa19918-3ea7-4059-acd8-abe601135106",
      "FormId": "3c8ebaec-09bf-4106-b451-ac850097c0f7",
      "EventSection": "AssistiveTechnologyNeeds",
      "FormState": "",
      "FormStatusKey": "Initial",
      "FormStatus": "Initial",
      "EventSectionGroupName": "<span class='hidden'>0000000025</span>Plan",
      "Name": "Assistive Technology Needs"
    },
    {
      "OrderNumber": "0000040000",
      "FormId": "",
      "EventSection": "AssistiveTechnology",
      "FormState": "",
      "FormStatusKey": "",
      "FormStatus": "",
      "EventSectionGroupName": "<span class='hidden'>0000000025</span>Plan",
      "Name": "Assistive Technology"
    },
    {
      "OrderNumber": "0000040000",
      "FormId": "",
      "EventSection": "ESYScheduleofServices",
      "FormState": "",
      "FormStatusKey": "",
      "FormStatus": "",
      "EventSectionGroupName": "<span class='hidden'>0000000035</span>ESY",
      "Name": "ESY Schedule of Services"
    },
    {
      "OrderNumber": "0000045001",
      "FormDefinitionId": "b251ecad-5d17-4239-83fd-abc701691227",
      "FormId": "5e788664-8e90-48b9-b87c-ac850097c0e4",
      "EventSection": "PhysicalFitnessAssessment",
      "FormState": "",
      "FormStatusKey": "Initial",
      "FormStatus": "Initial",
      "EventSectionGroupName": "<span class='hidden'>0000000025</span>Plan",
      "Name": "Physical Fitness Assessment"
    },
    {
      "OrderNumber": "0000045001",
      "FormDefinitionId": "db70e174-8c15-47f4-b88f-abdb0156e0a3",
      "FormId": "d9bfa36e-fd7f-45a5-9d7a-ac850097c0ee",
      "EventSection": "Graduation",
      "FormState": "",
      "FormStatusKey": "Initial",
      "FormStatus": "Initial",
      "EventSectionGroupName": "<span class='hidden'>0000000045</span>Supplements",
      "Name": "Graduation"
    },
    {
      "OrderNumber": "0000045001",
      "FormDefinitionId": "b179b12c-96c1-4687-aea5-bfcfd954c052",
      "FormId": "2b410878-cc4f-4d28-b8ce-ac850097c0db",
      "EventSection": "NoticeofProceduralSafeguards",
      "FormState": "*",
      "FormStatusKey": "Initial",
      "FormStatus": "Initial",
      "EventSectionGroupName": "<span class='hidden'>0000000500</span>Forms",
      "Name": "Notice of Procedural Safeguards"
    },
    {
      "OrderNumber": "0000050001",
      "FormDefinitionId": "108d9321-e934-4802-882c-af1a5ad4ac96",
      "FormId": "3bf479f5-bd00-4688-83c6-ac850097c0db",
      "EventSection": "StateAssessmentResults",
      "FormState": "",
      "FormStatusKey": "Initial",
      "FormStatus": "Initial",
      "EventSectionGroupName": "<span class='hidden'>0000000025</span>Plan",
      "Name": "State Assessment Results"
    },
    {
      "OrderNumber": "0000050001",
      "FormDefinitionId": "3bc300c5-1e27-4fa7-ab5e-abc901553cfb",
      "FormId": "a202d7ec-6a09-4650-ab9a-ac850097c0e4",
      "EventSection": "ESYTransportation",
      "FormState": "",
      "FormStatusKey": "Initial",
      "FormStatus": "Initial",
      "EventSectionGroupName": "<span class='hidden'>0000000035</span>ESY",
      "Name": "ESY Transportation"
    },
    {
      "OrderNumber": "0000050001",
      "FormDefinitionId": "fb0a6999-f767-4a7a-a7ed-40abd3f4deeb",
      "FormId": "b702ab84-e13a-42b4-a93b-ac850097c0e0",
      "EventSection": "MedicallyFragile",
      "FormState": "",
      "FormStatusKey": "Initial",
      "FormStatus": "Initial",
      "EventSectionGroupName": "<span class='hidden'>0000000045</span>Supplements",
      "Name": "Medically Fragile"
    },
    {
      "OrderNumber": "0000050001",
      "FormDefinitionId": "6f24fcd1-1c6c-4bc7-8aa9-abc201159c17",
      "FormId": "a5d51fe2-3412-4e6c-bd7f-ac850097c0e4",
      "EventSection": "SupportedDecision-MakingAgreementforAdultStudents",
      "FormState": "",
      "FormStatusKey": "Initial",
      "FormStatus": "Initial",
      "EventSectionGroupName": "<span class='hidden'>0000000500</span>Forms",
      "Name": "Supported Decision-Making Agreement for Adult Students"
    },
    {
      "OrderNumber": "0000050082",
      "FormDefinitionId": "0071b04a-5128-47f3-8e89-27a143d8933d",
      "FormId": "a1481f3c-60cc-41b4-9650-ac850097c0e0",
      "EventSection": "ARDData",
      "FormState": "",
      "FormStatusKey": "Initial",
      "FormStatus": "Initial",
      "EventSectionGroupName": "<span class='hidden'>0000000000</span>Summary",
      "Name": "ARD Data"
    },
    {
      "OrderNumber": "0000060001",
      "FormDefinitionId": "de4fad6b-257e-49ab-821f-9fc27056735a",
      "FormId": "4f9e9c83-8abd-44b7-847e-ac850097c0d6",
      "EventSection": "STAARAlternate2%2FMedicalExceptions%2FNAAR",
      "FormState": "",
      "FormStatusKey": "Initial",
      "FormStatus": "Initial",
      "EventSectionGroupName": "<span class='hidden'>0000000025</span>Plan",
      "Name": "STAAR Alternate 2 Participation Requirements"
    },
    {
      "OrderNumber": "0000060001",
      "FormDefinitionId": "33633aae-fe45-437f-8fe9-abe60151abdc",
      "FormId": "eaf0d032-42cb-4b8e-8829-ac850097c0f7",
      "EventSection": "Out-of-DistrictPlacement",
      "FormState": "",
      "FormStatusKey": "Initial",
      "FormStatus": "Initial",
      "EventSectionGroupName": "<span class='hidden'>0000000045</span>Supplements",
      "Name": "Out-of-District Placement"
    },
    {
      "OrderNumber": "0000060002",
      "FormDefinitionId": "9e02bb4f-5abc-46b0-a09e-ac3e008de435",
      "FormId": "b9b6ebd4-f45f-4e55-a538-ac850097c0f7",
      "EventSection": "STAARAlternate2%2FMedicalExceptions%2FNAAR",
      "FormState": "",
      "FormStatusKey": "Initial",
      "FormStatus": "Initial",
      "EventSectionGroupName": "<span class='hidden'>0000000025</span>Plan",
      "Name": "STAAR Alternate 2 Medical Exceptions"
    },
    {
      "OrderNumber": "0000060003",
      "FormDefinitionId": "3675118b-1e99-4a68-b2fa-ac3f00862e39",
      "FormId": "1a451a5a-c71c-431c-843d-ac850097c0f7",
      "EventSection": "STAARAlternate2%2FMedicalExceptions%2FNAAR",
      "FormState": "",
      "FormStatusKey": "Initial",
      "FormStatus": "Initial",
      "EventSectionGroupName": "<span class='hidden'>0000000025</span>Plan",
      "Name": "NAAR Eligibility"
    },
    {
      "OrderNumber": "0000070000",
      "FormId": "",
      "EventSection": "DistributionManager",
      "FormState": "*",
      "FormStatusKey": "",
      "FormStatus": "",
      "EventSectionGroupName": "<span class='hidden'>0000000000</span>Summary",
      "Name": "Distribution Manager"
    },
    {
      "OrderNumber": "0000070001",
      "FormDefinitionId": "70a861e4-bc29-4c0a-85f1-dae783529844",
      "FormId": "d4392c08-309c-4246-8809-ac850097c0db",
      "EventSection": "STAARParticipation",
      "FormState": "",
      "FormStatusKey": "Initial",
      "FormStatus": "Initial",
      "EventSectionGroupName": "<span class='hidden'>0000000025</span>Plan",
      "Name": "STAAR Participation"
    },
    {
      "OrderNumber": "0000070001",
      "FormDefinitionId": "5be60e2a-1100-4254-afc1-abe20133f17b",
      "FormId": "561a2e5e-d5e1-4e28-a305-ac850097c0f2",
      "EventSection": "Parent%2FIn-HomeTraining",
      "FormState": "",
      "FormStatusKey": "Initial",
      "FormStatus": "Initial",
      "EventSectionGroupName": "<span class='hidden'>0000000045</span>Supplements",
      "Name": "Parent/ In-Home Training"
    },
    {
      "OrderNumber": "0000080000",
      "FormId": "",
      "EventSection": "STAARAccommodations",
      "FormState": "",
      "FormStatusKey": "",
      "FormStatus": "",
      "EventSectionGroupName": "<span class='hidden'>0000000025</span>Plan",
      "Name": "STAAR Accommodations"
    },
    {
      "OrderNumber": "0000080001",
      "FormDefinitionId": "b262ecab-497c-49d6-8305-abe600e013a1",
      "FormId": "48421fb4-98d2-4f64-a54d-ac850097c0f2",
      "EventSection": "Parent%2FIn-HomeTrainingNeedsAssessment",
      "FormState": "",
      "FormStatusKey": "Initial",
      "FormStatus": "Initial",
      "EventSectionGroupName": "<span class='hidden'>0000000045</span>Supplements",
      "Name": "Parent/In-Home Training Needs Assessment"
    },
    {
      "OrderNumber": "0000090000",
      "FormId": "",
      "EventSection": "TELPASAssessmentResults",
      "FormState": "",
      "FormStatusKey": "",
      "FormStatus": "",
      "EventSectionGroupName": "<span class='hidden'>0000000025</span>Plan",
      "Name": "TELPAS Assessment Results"
    },
    {
      "OrderNumber": "0000090001",
      "FormDefinitionId": "268c3341-7cdf-4bc6-a41d-e49fa6cf5290",
      "FormId": "e2108bc0-1ccd-474d-a18b-ac850097c0e0",
      "EventSection": "PersonalCareServices",
      "FormState": "",
      "FormStatusKey": "Initial",
      "FormStatus": "Initial",
      "EventSectionGroupName": "<span class='hidden'>0000000045</span>Supplements",
      "Name": "Personal Care Services"
    },
    {
      "OrderNumber": "0000100001",
      "FormDefinitionId": "af54d458-a58a-4ec5-8a58-732c76893685",
      "FormId": "04bb7a03-6361-4ff4-851a-ac850097c0db",
      "EventSection": "TELPASAlternateParticipationRequirements",
      "FormState": "",
      "FormStatusKey": "Initial",
      "FormStatus": "Initial",
      "EventSectionGroupName": "<span class='hidden'>0000000025</span>Plan",
      "Name": "TELPAS Alternate Participation Requirements"
    },
    {
      "OrderNumber": "0000100001",
      "FormDefinitionId": "4a09d1d5-92cd-4385-a030-7d57989c8dde",
      "FormId": "a684729c-e30a-4a5f-864b-ac850097c0d6",
      "EventSection": "Signatures",
      "FormState": "*",
      "FormStatusKey": "Initial",
      "FormStatus": "Initial",
      "EventSectionGroupName": "<span class='hidden'>0000000030</span>Meeting Participation",
      "Name": "Signatures"
    },
    {
      "OrderNumber": "0000100001",
      "FormDefinitionId": "56761715-ae21-4d6c-b5ea-abdd01063e2f",
      "FormId": "8e15fb73-eb5d-4faf-8c42-ac850097c0f2",
      "EventSection": "RDSPD",
      "FormState": "",
      "FormStatusKey": "Initial",
      "FormStatus": "Initial",
      "EventSectionGroupName": "<span class='hidden'>0000000045</span>Supplements",
      "Name": "RDSPD"
    },
    {
      "OrderNumber": "0000110001",
      "FormDefinitionId": "b4e34af9-e73c-47bd-92fa-874728d773d3",
      "FormId": "469eb915-3c42-42db-b445-ac850097c0db",
      "EventSection": "TELPASParticipation",
      "FormState": "",
      "FormStatusKey": "Initial",
      "FormStatus": "Initial",
      "EventSectionGroupName": "<span class='hidden'>0000000025</span>Plan",
      "Name": "TELPAS Participation"
    },
    {
      "OrderNumber": "0000110001",
      "FormDefinitionId": "7d161e00-02b8-4be6-a7bf-abdc00e7b51a",
      "FormId": "abb635f6-2b8c-421a-abd3-ac850097c0ee",
      "EventSection": "SkilledNursingServices",
      "FormState": "",
      "FormStatusKey": "Initial",
      "FormStatus": "Initial",
      "EventSectionGroupName": "<span class='hidden'>0000000045</span>Supplements",
      "Name": "Skilled Nursing Services"
    },
    {
      "OrderNumber": "0000115001",
      "FormDefinitionId": "96f2e5e8-53a2-41e1-ae9e-abc70157e344",
      "FormId": "19a1d4a9-3267-4f9b-bcae-ac850097c0e4",
      "EventSection": "TELPASAccommodations",
      "FormState": "",
      "FormStatusKey": "Initial",
      "FormStatus": "Initial",
      "EventSectionGroupName": "<span class='hidden'>0000000025</span>Plan",
      "Name": "TELPAS Accommodations"
    },
    {
      "OrderNumber": "0000120000",
      "FormId": "",
      "EventSection": "DistrictAssessmentResults",
      "FormState": "",
      "FormStatusKey": "",
      "FormStatus": "",
      "EventSectionGroupName": "<span class='hidden'>0000000025</span>Plan",
      "Name": "District Assessment Results"
    },
    {
      "OrderNumber": "0000120001",
      "FormDefinitionId": "cc24a88c-2f7e-4b74-8ee7-abc00149a23e",
      "FormId": "7ad06abc-2cb7-4067-9b8a-ac850097c0e0",
      "EventSection": "Transition",
      "FormState": "",
      "FormStatusKey": "Initial",
      "FormStatus": "Initial",
      "EventSectionGroupName": "<span class='hidden'>0000000045</span>Supplements",
      "Name": "Transition"
    },
    {
      "OrderNumber": "0000120001",
      "FormDefinitionId": "d63d7446-f5e1-4bab-a7e8-abdb0130d66e",
      "FormId": "b9050202-cb45-406d-9cb4-ac850097c0ee",
      "EventSection": "VisualImpairment",
      "FormState": "",
      "FormStatusKey": "Initial",
      "FormStatus": "Initial",
      "EventSectionGroupName": "<span class='hidden'>0000000045</span>Supplements",
      "Name": "Visual Impairment"
    },
    {
      "OrderNumber": "0000125001",
      "FormDefinitionId": "ee49b55d-4c98-4fdb-b7aa-8c90b8b3eac8",
      "FormId": "d04dffeb-bda2-4e4d-90fc-ac850097c0db",
      "EventSection": "DistrictAssessmentsandAccommodations",
      "FormState": "",
      "FormStatusKey": "Initial",
      "FormStatus": "Initial",
      "EventSectionGroupName": "<span class='hidden'>0000000025</span>Plan",
      "Name": "District Assessments and Accommodations"
    },
    {
      "OrderNumber": "0000130000",
      "FormId": "",
      "EventSection": "ScheduleofServices",
      "FormState": "*",
      "FormStatusKey": "",
      "FormStatus": "",
      "EventSectionGroupName": "<span class='hidden'>0000000025</span>Plan",
      "Name": "Schedule of Services"
    },
    {
      "OrderNumber": "0000135001",
      "FormDefinitionId": "192fc3da-dc30-4142-8c34-22ef109480a1",
      "FormId": "0365ec44-d5d2-43a2-8d77-ac850097c0db",
      "EventSection": "Transportation",
      "FormState": "",
      "FormStatusKey": "Initial",
      "FormStatus": "Initial",
      "EventSectionGroupName": "<span class='hidden'>0000000025</span>Plan",
      "Name": "Transportation"
    },
    {
      "OrderNumber": "0000136001",
      "FormDefinitionId": "b5cbd4f4-3936-4845-ae7b-abd0011a13af",
      "FormId": "4303010a-084b-4c9c-9eb5-ac850097c0e9",
      "EventSection": "LREServiceAlternatives",
      "FormState": "",
      "FormStatusKey": "Initial",
      "FormStatus": "Initial",
      "EventSectionGroupName": "<span class='hidden'>0000000025</span>Plan",
      "Name": "LRE Service Alternatives"
    },
    {
      "OrderNumber": "0000145001",
      "FormDefinitionId": "142ce309-2b02-4c51-acb0-abc7017524b3",
      "FormId": "e7676653-1778-4b43-8a0b-ac850097c0e4",
      "EventSection": "LRERemovalfromGeneralEducation",
      "FormState": "",
      "FormStatusKey": "Initial",
      "FormStatus": "Initial",
      "EventSectionGroupName": "<span class='hidden'>0000000025</span>Plan",
      "Name": "LRE Removal from General Education"
    },
    {
      "OrderNumber": "0000150000",
      "FormId": "",
      "EventSection": "LRE%26EducationalPlacement",
      "FormState": "*",
      "FormStatusKey": "",
      "FormStatus": "",
      "EventSectionGroupName": "<span class='hidden'>0000000025</span>Plan",
      "Name": "LRE & Educational Placement"
    },
    {
      "OrderNumber": "0000155001",
      "FormDefinitionId": "f3759ac3-60a4-426f-9c7d-abea00ec7897",
      "FormId": "bc475de4-4d8d-4b55-8004-ac850097c0f7",
      "EventSection": "Assurances",
      "FormState": "",
      "FormStatusKey": "Initial",
      "FormStatus": "Initial",
      "EventSectionGroupName": "<span class='hidden'>0000000025</span>Plan",
      "Name": "Assurances"
    },
    {
      "OrderNumber": "0000160001",
      "FormDefinitionId": "1ab0b59e-0a50-4d1c-88e7-abc6016e20a7",
      "FormId": "50dd6923-03de-4004-8db4-ac850097c0e4",
      "EventSection": "AccesstoandDestructionofRecords",
      "FormState": "",
      "FormStatusKey": "Initial",
      "FormStatus": "Initial",
      "EventSectionGroupName": "<span class='hidden'>0000000025</span>Plan",
      "Name": "Access to and Destruction of Records"
    },
    {
      "OrderNumber": "0000165001",
      "FormDefinitionId": "dbdaa57f-457b-4e11-97a1-abe600b01b0c",
      "FormId": "0edf30e8-eea5-4f3e-9aca-ac850097c0f2",
      "EventSection": "ReviewofCommitteeDecisions",
      "FormState": "",
      "FormStatusKey": "Initial",
      "FormStatus": "Initial",
      "EventSectionGroupName": "<span class='hidden'>0000000025</span>Plan",
      "Name": "Review of Committee Decisions"
    },
    {
      "OrderNumber": "0000175001",
      "FormDefinitionId": "bb2ad644-86b2-4253-a726-36a51732d795",
      "FormId": "beb1a82b-78cc-4806-9bb3-ac850097c0e0",
      "EventSection": "Agreement",
      "FormState": "",
      "FormStatusKey": "Initial",
      "FormStatus": "Initial",
      "EventSectionGroupName": "<span class='hidden'>0000000025</span>Plan",
      "Name": "Agreement"
    },
    {
      "OrderNumber": "0000220000",
      "FormId": "",
      "EventSection": "Eligibilities%2FImpairments",
      "FormState": "",
      "FormStatusKey": "",
      "FormStatus": "",
      "EventSectionGroupName": "<span class='hidden'>0000000015</span>Eligibilities/Impairments",
      "Name": "Eligibilities/Impairments"
    },
    {
      "OrderNumber": "0009000000",
      "FormId": "",
      "EventSection": "ContactLog%2FNotes",
      "FormState": "",
      "FormStatusKey": "",
      "FormStatus": "",
      "EventSectionGroupName": "<span class='hidden'>9000</span>Contact Log/Notes",
      "Name": "Contact Log/Notes"
    },
    {
      "OrderNumber": "0009500000",
      "FormId": "",
      "EventSection": "Attachments",
      "FormState": "",
      "FormStatusKey": "",
      "FormStatus": "",
      "EventSectionGroupName": "<span class='hidden'>9500</span>Attachments",
      "Name": "Attachments"
    }
  ],
  "Total": 66
}